{
    "dataset": {
        "title": "2024_NIA_LAB_LAB_PG_F_A1_C2C_PG_N_02762.JSON",
        "date": "2024.10.26",
        "time": "N",
        "weather": "Sunny",
        "scenario": "Test",
        "length": "00:02:00"
    },
    "Collection_info": {
        "Car info": "Sedan",
        "Driver_ID": "000016",
        "Sex": "F",
        "Age": "A1",
        "Driving Experience": "E1",
        "Traffic": "other"
    },
    "Load": {
        "Load_category": "PG",
        "Load_Geo": "single"
    },
    "Risky": {
        "Risky_type": "C2C"
    },
    "time": {
        "Pre_start_time": "00:00:00",
        "Pre_end_time": "00:00:23",
        "Post_start_time": "00:01:46",
        "Post_end_time": "00:02:00"
    },
    "labeling": {
        "SEN_1": "운전자의 눈은 우측을 보고 있고 손은 핸들을 조작하고 있다.",
        "SEN_2": "운전자의 눈은 정면을 보고 있고 손은 핸들을 조작하고 있다.",
        "SEN_3": "주행 차량은 직진하고 있고 주변에 다른 차량은 보이지 않는다. 날씨 및 도로포장 상태는 알 수 없다.",
        "SEN_4": "주행 차량은 직진하고 있고 전방에 낙하물이 떨어져 있다. 날씨는 알 수 없고 도로포장 상태도 알 수 없다.",
        "SEN_5": "위험구간 전에는 운전자의 눈은 우측을 보고 있고 손은 핸들을 조작하고 있다. 주행 차량은 직진하고 있고 주변에 다른 차량은 보이지 않는다. 날씨 상태는 알 수 없고 도로 포장 상태는 알 수 없다. 위험구간 후에는 운전자의 눈은 정면을 보고 있고 손은 핸들을 조작하고 있다. 주행 차량은 직진하고 있고 전방에 낙하물이 떨어져 있다. 날씨는 알 수 없고 도로 포장 상태도 알 수 없다. 차의 속도는 정속 주행 중이다."
    }
}